meya/__init__.py
meya/_component.py
meya/cms.py
meya/db.py
meya/main.py
meya/cards/__init__.py
meya_components-1.0.dist-info/METADATA
meya_components-1.0.dist-info/RECORD
meya_components-1.0.dist-info/WHEEL
meya_components-1.0.dist-info/top_level.txt
meyacards/__init__.py
meyacards/attachment.py
meyacards/base.py
meyacards/engine.py
meyacards/event.py
meyacards/generic.py
meyacards/human.py
meyacards/image.py
meyacards/list.py
meyacards/location.py
meyacards/receipt.py
meyacards/text.py
meyacards/utilities.py
meyacards/controls/__init__.py
meyacards/controls/buttons.py
meyastore/__init__.py
meyastore/base.py
meyastore/bot.py
meyastore/content.py
meyastore/list.py
meyastore/logging.py
meyastore/request.py
meyastore/table.py
meyastore/user.py
